setup.py
Flask_FedoraCommons.egg-info/PKG-INFO
Flask_FedoraCommons.egg-info/SOURCES.txt
Flask_FedoraCommons.egg-info/dependency_links.txt
Flask_FedoraCommons.egg-info/not-zip-safe
Flask_FedoraCommons.egg-info/requires.txt
Flask_FedoraCommons.egg-info/top_level.txt
flask_fedora_commons/__init__.py
flask_fedora_commons/lib/__init__.py
flask_fedora_commons/lib/api.py
flask_fedora_commons/lib/server.py
flask_fedora_commons/lib/util.py