Metadata-Version: 1.1
Name: Flask-FedoraCommons
Version: 0.0.5
Summary: Library for manipulating Fedora Commons digitial repositories
Home-page: http://github.com/jermnelson/flask-fedora-commons
Author: Jeremy Nelson
Author-email: jermnelson@gmail.com
License: MIT License
Platform: any
Classifier: Framework :: Flask
Classifier: Environment :: Web Environment
Classifier: Intended Audience :: Developers
Classifier: License :: OSI Approved :: MIT License
Classifier: Operating System :: OS Independent
Classifier: Programming Language :: Python
Classifier: Topic :: Internet :: WWW/HTTP :: Dynamic Content
Classifier: Topic :: Software Development :: Libraries :: Python Modules
